compare_meshes_wasi/__init__.py
compare_meshes_wasi/_version.py
compare_meshes_wasi/compare_meshes.py
compare_meshes_wasi/wasm_modules/compare-meshes.wasi.wasm
compare_meshes_wasi-0.1.0.dist-info/METADATA
compare_meshes_wasi-0.1.0.dist-info/WHEEL
compare_meshes_wasi-0.1.0.dist-info/RECORD
